eruption/__init__.py
eruption/canvas.py
eruption/color.py
eruption/connection.py
eruption/hardware.py
eruption/util.py
eruption/transport/__init__.py
eruption/transport/local.py
eruption/transport/sdk_support_pb2.py
eruption_sdk-0.0.10.dist-info/METADATA
eruption_sdk-0.0.10.dist-info/WHEEL
eruption_sdk-0.0.10.dist-info/licenses/LICENSE
eruption_sdk-0.0.10.dist-info/RECORD
