Metadata-Version: 2.1
Name: eruption-sdk
Version: 0.0.10
Summary: Provides an interface to the Eruption Realtime RGB LED Driver for Linux
Project-URL: Homepage, https://github.com/X3n0m0rph59/eruption
Project-URL: Bug Tracker, https://github.com/X3n0m0rph59/eruption/issues
Author-email: X3n0m0rph59 <x3n0m0rph59@gmail.com>
License-File: LICENSE
Keywords: driver,eruption,led,linux,sdk
Classifier: Development Status :: 4 - Beta
Classifier: Intended Audience :: Developers
Classifier: License :: OSI Approved :: GNU Lesser General Public License v3 (LGPLv3)
Classifier: Operating System :: POSIX :: Linux
Classifier: Programming Language :: Python :: 3
Classifier: Topic :: System :: Hardware :: Hardware Drivers
Requires-Python: >=3.7
Requires-Dist: protobuf<=3.20
